LICENSE
MANIFEST.in
README.md
pyproject.toml
requirements.txt
src/blib/__init__.py
src/blib/base.py
src/blib/colormap.py
src/blib/colors.py
src/blib/cosmetics.py
src/blib/dailylog.py
src/blib/font.py
src/blib/traffic.py
src/blib/utils.py
src/blib/fonts/NotoSans-Black.ttf
src/blib/fonts/NotoSans-Bold.ttf
src/blib/fonts/NotoSans-ExtraBold.ttf
src/blib/fonts/NotoSans-ExtraLight.ttf
src/blib/fonts/NotoSans-Light.ttf
src/blib/fonts/NotoSans-Medium.ttf
src/blib/fonts/NotoSans-Regular.ttf
src/blib/fonts/NotoSans-SemiBold.ttf
src/blib/fonts/NotoSans-Thin.ttf
src/blib_py.egg-info/PKG-INFO
src/blib_py.egg-info/SOURCES.txt
src/blib_py.egg-info/dependency_links.txt
src/blib_py.egg-info/requires.txt
src/blib_py.egg-info/top_level.txt