Metadata-Version: 2.2
Name: blib-py
Version: 1.5.6
Summary: Boonleng's Python Library
Author-email: Boonleng Cheong <boonleng@ou.edu>
License: MIT License
Project-URL: Repository, https://github.com/boonleng/blib-py
Classifier: Development Status :: 5 - Production/Stable
Classifier: Intended Audience :: Developers
Classifier: Intended Audience :: Science/Research
Classifier: License :: OSI Approved :: MIT License
Classifier: Operating System :: OS Independent
Classifier: Programming Language :: Python :: 3
Classifier: Topic :: Scientific/Engineering
Classifier: Topic :: Software Development :: Libraries
Classifier: Topic :: Software Development :: Libraries :: Python Modules
Requires-Python: >=3.8
License-File: LICENSE
Requires-Dist: numpy
Requires-Dist: matplotlib
